[
    {
        "id": 1,
        "name": "noman",
        "email": "noman.apparel.4003@gmail.com",
        "specialist": "gastrology",
        "degree": "mbbs",
        "img": "https://randomuser.me/api/portraits/women/95.jpg",
        "facebook": "https: //www.facebook.com/noman.apparel.4003",
        "linkedIn": "https: //www.facebook.com/noman.apparel.4003"
    },
    {
        "id": 1,
        "name": "noman",
        "email": "noman.apparel.4003@gmail.com",
        "specialist": "gastrology",
        "degree": "mbbs",
        "img": "https://randomuser.me/api/portraits/men/4.jpg",
        "facebook": "https: //www.facebook.com/noman.apparel.4003",
        "linkedIn": "https: //www.facebook.com/noman.apparel.4003"
    },
    {
        "id": 1,
        "name": "noman",
        "email": "noman.apparel.4003@gmail.com",
        "specialist": "gastrology",
        "degree": "mbbs",
        "img": "https://randomuser.me/api/portraits/men/73.jpg",
        "facebook": "https: //www.facebook.com/noman.apparel.4003",
        "linkedIn": "https: //www.facebook.com/noman.apparel.4003"
    }
]